{"authorDailyContributionsMap":{"Kang-Quan":[{"date":"2022-08-17","commitResults":[{"hash":"5c48678d6a5869eac0423a78bb3142f2e4aa9b4a","messageTitle":"Add echo and bye to duke","messageBody":"","tags":["Level-1"],"fileTypesAndContributionMap":{"java":{"insertions":25,"deletions":0}}}]},{"date":"2022-08-18","commitResults":[{"hash":"717acb7433875fb5e75e0eb846d5a0f694cbe2ea","messageTitle":"Add list and add to duke","messageBody":"","tags":["Level-2"],"fileTypesAndContributionMap":{"java":{"insertions":35,"deletions":9}}},{"hash":"e1f8319a36ec1eccf4ce4e6ea9781d45804f4929","messageTitle":"Add mark as done and undo mark as done to duke","messageBody":"","tags":["Level-3"],"fileTypesAndContributionMap":{"java":{"insertions":109,"deletions":10}}},{"hash":"f083b27da6228a3eb5873b04371b5fda43385991","messageTitle":"Add ToDos, Events and Deadlines to duke","messageBody":"","tags":["Level-4"],"fileTypesAndContributionMap":{"java":{"insertions":99,"deletions":17}}},{"hash":"8e902adb7105615fefc343e5b8f7068d96b574c2","messageTitle":"Add TextUiTesting to duke","messageBody":"","tags":["A-TextUiTesting"],"fileTypesAndContributionMap":{"txt":{"insertions":9,"deletions":0}}},{"hash":"3ee3eb235729a9707132faf9affb0fd1b8d03f93","messageTitle":"Add handle error message to duke","messageBody":"","tags":["Level-5"],"fileTypesAndContributionMap":{"java":{"insertions":111,"deletions":67}}},{"hash":"dc6a56ab7a2190cc0875ace8e29a4d873ed5d739","messageTitle":"Add delete function to duke","messageBody":"","tags":["Level-6"],"fileTypesAndContributionMap":{"java":{"insertions":18,"deletions":0}}},{"hash":"55bb4b75fad93bfa28279ca7664f8f399c007df4","messageTitle":"Add enum to replace keyword","messageBody":"","tags":["A-Enums"],"fileTypesAndContributionMap":{"java":{"insertions":50,"deletions":34}}}]},{"date":"2022-08-24","commitResults":[{"hash":"da32da898e3a1cecde7fbf9be3447ef811e5b8d1","messageTitle":"Add save function to duke","messageBody":"","tags":["Level-7"],"fileTypesAndContributionMap":{"txt":{"insertions":0,"deletions":0},"java":{"insertions":140,"deletions":0}}}]},{"date":"2022-08-25","commitResults":[{"hash":"0798faf82c615772c3767ae0743d0b8829c4c1d0","messageTitle":"Add date, time to event and deadline tasks","messageBody":"","tags":["Level-8"],"fileTypesAndContributionMap":{"java":{"insertions":42,"deletions":16}}},{"hash":"a701a0d2f7db1b2ec576ceece71d3b925bcf17af","messageTitle":"Fix bug in loading SavedTask.txt to list","messageBody":"","fileTypesAndContributionMap":{"java":{"insertions":33,"deletions":11}}}]},{"date":"2022-08-28","commitResults":[{"hash":"099a302d6d996c48d49bdbc20745af3061b79ecf","messageTitle":"Refactor code into OOP","messageBody":"","tags":["A-MoreOOP"],"fileTypesAndContributionMap":{"java":{"insertions":633,"deletions":356}}},{"hash":"ca0aec90cee09c6b03ae79fc4267e433734bdb11","messageTitle":"Add package to duke","messageBody":"","tags":["A-Packages"],"fileTypesAndContributionMap":{"txt":{"insertions":2,"deletions":0},"java":{"insertions":88,"deletions":0}}}]},{"date":"2022-08-29","commitResults":[{"hash":"2390b2f22a09417739ae229364882667a14adf30","messageTitle":"Add gradle to duke","messageBody":"","tags":["A-Gradle"],"fileTypesAndContributionMap":{"gradle":{"insertions":1,"deletions":1},"txt":{"insertions":3,"deletions":2}}},{"hash":"f75604ad3a842d4a2971858dfe09fb744a6ed590","messageTitle":"Add junit test to class TestList","messageBody":"","tags":["A-Jar","A-JUnit"],"fileTypesAndContributionMap":{"java":{"insertions":27,"deletions":0}}}]},{"date":"2022-08-30","commitResults":[{"hash":"e4bfcc0d56d2a11d87d5e5a8a28c85ca6fd35ed3","messageTitle":"Add javadoc to duke","messageBody":"","tags":["A-JavaDoc"],"fileTypesAndContributionMap":{"java":{"insertions":371,"deletions":12}}},{"hash":"500b0a94b1f987fc0d274f5c32f5bd3146059c70","messageTitle":"Refactor code according to coding standard","messageBody":"","tags":["A-CodingStandard"],"fileTypesAndContributionMap":{"java":{"insertions":194,"deletions":199}}}]},{"date":"2022-08-31","commitResults":[{"hash":"3f4e09d8c1836eeaf523a4806b587b272e19077a","messageTitle":"Add find function to duke","messageBody":"","tags":["Level-9"],"fileTypesAndContributionMap":{"java":{"insertions":58,"deletions":0}}}]},{"date":"2022-09-07","commitResults":[{"hash":"c3c93c9c68f364d43ac795bb36708e826cc923a8","messageTitle":"Add GUI to duke","messageBody":"","tags":["Level-10"],"fileTypesAndContributionMap":{"gradle":{"insertions":25,"deletions":1},"txt":{"insertions":12,"deletions":3},"fxml":{"insertions":48,"deletions":0},"java":{"insertions":432,"deletions":212},"bat":{"insertions":1,"deletions":1},"md":{"insertions":2,"deletions":2}}}]}]},"authorFileTypeContributionMap":{"Kang-Quan":{"java":1539,"md":2,"fxml":48,"sh":0,"bat":1,"gradle":25,"txt":21}},"authorContributionVariance":{"Kang-Quan":81894.32},"authorDisplayNameMap":{"Kang-Quan":"CS2103T-W08-4 LEE ..QUAN"}}
